LICENSE
README.md
setup.py
CVE_2018_0296.egg-info/PKG-INFO
CVE_2018_0296.egg-info/SOURCES.txt
CVE_2018_0296.egg-info/dependency_links.txt
CVE_2018_0296.egg-info/entry_points.txt
CVE_2018_0296.egg-info/requires.txt
CVE_2018_0296.egg-info/top_level.txt
cve20180296/__init__.py
cve20180296/main.py
cve20180296/includes/__init__.py
cve20180296/includes/bot.py
cve20180296/includes/filereader.py
cve20180296/includes/scan.py
cve20180296/includes/writefile.py
cve20180296/utils/__init__.py
cve20180296/utils/configure.py
cve20180296/utils/const.py
cve20180296/utils/helpers.py
cve20180296/utils/status.py